{
  "name": "Code-XR Demo",
  "image": "mcr.microsoft.com/devcontainers/base:ubuntu-22.04",
  
  // Extensiones necesarias para la demo
  "customizations": {
    "vscode": {
      "extensions": [
        "aMonteSl.code-xr",
        "ms-vscode.vscode-typescript-next",
        "ms-python.python",
        "ms-vscode.cpptools",
        "redhat.java"
      ],
      "settings": {
        "terminal.integrated.defaultProfile.linux": "bash",
        "workbench.colorTheme": "Default Dark+",
        "editor.fontSize": 14,
        "editor.tabSize": 2,
        "files.autoSave": "afterDelay",
        "explorer.confirmDelete": false,
        "git.enableSmartCommit": true,
        "workbench.startupEditor": "readme"
      }
    }
  },

  // Caracter铆sticas adicionales para un mejor entorno de desarrollo
  "features": {
    "ghcr.io/devcontainers/features/node:1": {
      "version": "lts"
    },
    "ghcr.io/devcontainers/features/python:1": {
      "version": "3.11"
    },
    "ghcr.io/devcontainers/features/git:1": {}
  },

  // Configuraci贸n de puertos para desarrollo web
  "forwardPorts": [3000, 8080, 5000],
  "portsAttributes": {
    "3000": {
      "label": "Frontend Dev Server"
    },
    "8080": {
      "label": "Backend Server"
    },
    "5000": {
      "label": "Python Server"
    }
  },

  // Comandos post-creaci贸n para preparar el entorno
  "postCreateCommand": "bash .devcontainer/setup.sh",
  
  // Comando de inicio para mostrar informaci贸n 煤til
  "postStartCommand": "echo ' Code-XR Demo Environment Ready! Check README.md for usage instructions.'",

  // Mejoras de rendimiento
  "mounts": [
    "source=${localWorkspaceFolder}/.vscode,target=/workspaceFolder/.vscode,type=bind,consistency=cached"
  ],

  // Configuraci贸n del usuario
  "remoteUser": "vscode"
}
